sparc_spy/__init__.py
sparc_spy/meshes.py
sparc_spy/scaffold.py
sparc_spy/util.py
sparc_spy-0.1.5.dist-info/LICENSE
sparc_spy-0.1.5.dist-info/METADATA
sparc_spy-0.1.5.dist-info/WHEEL
sparc_spy-0.1.5.dist-info/top_level.txt
sparc_spy-0.1.5.dist-info/RECORD
