Metadata-Version: 2.1
Name: sparc_spy
Version: 0.1.5
Summary: A python tool to enhance the accessibility of SPARC scaffold visualisations and their analyses in accordance with FAIR principles.
Home-page: https://github.com/SPARC-FAIR-Codeathon/sparc-spy
Author: SPARC SPy Team
License-File: LICENSE
Requires-Dist: ruff ==0.3.5
Requires-Dist: pre-commit ==3.8.0
Requires-Dist: pandas ==2.2.2
Requires-Dist: hurry.filesize ==0.9
Requires-Dist: tabulate ==0.9.0
Requires-Dist: sparc-me ==3.0.0
Requires-Dist: numpy ==1.26.4
Requires-Dist: pyvista ==0.44.1
